modpack_changelogger/__init__.py
modpack_changelogger/__main__.py
modpack_changelogger/cli_wrapper.py
modpack_changelogger/compare_packs.py
modpack_changelogger/config_handler.py
modpack_changelogger/extract_pack_data.py
modpack_changelogger/get_json.py
modpack_changelogger/get_mod_names.py
modpack_changelogger/main.py
modpack_changelogger/out.py
modpack_changelogger/overrides_detection.py
modpack_changelogger/utils.py
modpack_changelogger/version.py
modpack_changelogger-1.1.0.dist-info/licenses/LICENSE
test/test_.py
test/utils/Generate expected.py
modpack_changelogger-1.1.0.dist-info/METADATA
modpack_changelogger-1.1.0.dist-info/WHEEL
modpack_changelogger-1.1.0.dist-info/entry_points.txt
modpack_changelogger-1.1.0.dist-info/top_level.txt
modpack_changelogger-1.1.0.dist-info/RECORD
