Metadata-Version: 2.4
Name: modpack_changelogger
Version: 1.1.0
Summary: A powerful and customizable Python tool to generate a changelog between two Minecraft modpacks in modrinth.mrpack or curseforge.zip format.
Author-email: TheBossMagnus <thebossmagnus@proton.me>
License: MIT License
Project-URL: Homepage, https://github.com/TheBossMagnus/modpack-changelogger
Project-URL: Repository, https://github.com/TheBossMagnus/modpack-changelogger
Classifier: License :: OSI Approved :: MIT License
Classifier: Programming Language :: Python :: 3.8
Classifier: Programming Language :: Python :: 3.9
Classifier: Programming Language :: Python :: 3.10
Classifier: Programming Language :: Python :: 3.11
Classifier: Programming Language :: Python :: 3.12
Classifier: Programming Language :: Python :: 3.13
Requires-Python: >=3.8
License-File: LICENSE
Requires-Dist: aiohttp
Requires-Dist: click
Dynamic: license-file
